{"tabla_IDS_Planta":[{"@odata.etag":"","ItemInternalId":"949a91fe-9af6-4cfa-9006-1e4c909a9bbe","Mes":"5","Año":"2026","DNI":"74589085","APELLIDOS Y NOMBRES":"FUENTES-DAVILA QUELOPANA MAURICIO","ÁREA":"Administración","CARGO":"Administrador","GUARDIA":"B","Indicador":"INSPECCION","PROGRAMADO":"2","EJECUTADO":"3"},{"@odata.etag":"","ItemInternalId":"7d43e9a8-cea6-46d2-ad42-d325acb11e0d","Mes":"5","Año":"2026","DNI":"45789632","APELLIDOS Y NOMBRES":"CARRASCO JARAMILLO NATALIA","ÁREA":"Bienestar Social","CARGO":"Bienestar Social","GUARDIA":"B","Indicador":"INSPECCION","PROGRAMADO":"2","EJECUTADO":"2"},{"@odata.etag":"","ItemInternalId":"08cc949d-93ea-4429-b3e9-39809cf2c9d8","Mes":"5","Año":"2026","DNI":"48556725","APELLIDOS Y NOMBRES":"GARCIA LAVADO ABEL","ÁREA":"Operaciones","CARGO":"Jefe de Guardia","GUARDIA":"C","Indicador":"INSPECCION","PROGRAMADO":"1","EJECUTADO":"2"},{"@odata.etag":"","ItemInternalId":"353c8030-1389-4ef0-abbc-5e314f0b4ae8","Mes":"5","Año":"2026","DNI":"44359932","APELLIDOS Y NOMBRES":"VARGAS CASTRO MIGUEL","ÁREA":"Operaciones","CARGO":"Jefe de Guardia","GUARDIA":"B","Indicador":"INSPECCION","PROGRAMADO":"1","EJECUTADO":"2"},{"@odata.etag":"","ItemInternalId":"fa9516b2-73a3-44c6-b418-1304cc7fb898","Mes":"5","Año":"2026","DNI":"44872088","APELLIDOS Y NOMBRES":"PACHECO HIRAOKA WILMER","ÁREA":"Operaciones","CARGO":"Jefe de Guardia","GUARDIA":"A","Indicador":"INSPECCION","PROGRAMADO":"1","EJECUTADO":"0"},{"@odata.etag":"","ItemInternalId":"8dd1f5ac-b1d7-4cd5-8212-9443582a6571","Mes":"5","Año":"2026","DNI":"46336044","APELLIDOS Y NOMBRES":"ACUÑA QUISPE DAYGURO","ÁREA":"Laboratorio","CARGO":"Jefe de Laboratorio Quimico","GUARDIA":"B","Indicador":"INSPECCION","PROGRAMADO":"2","EJECUTADO":"0"},{"@odata.etag":"","ItemInternalId":"40fab485-1418-422e-ac33-4047d42b428b","Mes":"5","Año":"2026","DNI":"18144216","APELLIDOS Y NOMBRES":"CELIO RAMIREZ ANTONIO","ÁREA":"Mantenimiento","CARGO":"Jefe de Mantenimiento Electrico","GUARDIA":"C","Indicador":"INSPECCION","PROGRAMADO":"2","EJECUTADO":"2"},{"@odata.etag":"","ItemInternalId":"3b727f97-03f1-4a39-bbad-ebb2016c29d0","Mes":"5","Año":"2026","DNI":"70086433","APELLIDOS Y NOMBRES":"VEGA CASIANO ROMULO","ÁREA":"Mantenimiento","CARGO":"Jefe de Mantenimiento Vehicular","GUARDIA":"C","Indicador":"INSPECCION","PROGRAMADO":"2","EJECUTADO":"2"},{"@odata.etag":"","ItemInternalId":"89b362be-f1d9-4986-ad09-54d2c8580cd7","Mes":"5","Año":"2026","DNI":"77675654","APELLIDOS Y NOMBRES":"GORDILLO VELASQUES CRISTPHER","ÁREA":"Metalurgia","CARGO":"Jefe de Metalurgia","GUARDIA":"B","Indicador":"INSPECCION","PROGRAMADO":"0","EJECUTADO":"0"},{"@odata.etag":"","ItemInternalId":"66ff0f7c-ee41-45f2-ba07-f2a18ea4672b","Mes":"5","Año":"2026","DNI":"70458908","APELLIDOS Y NOMBRES":"PONCIANO JUSTO JOHNNY","ÁREA":"Producción","CARGO":"Jefe de Planta","GUARDIA":"B","Indicador":"INSPECCION","PROGRAMADO":"2","EJECUTADO":"2"},{"@odata.etag":"","ItemInternalId":"c0a39bd4-6c00-4720-9c68-31cb02560946","Mes":"5","Año":"2026","DNI":"46660606","APELLIDOS Y NOMBRES":"GOMEZ ROSAS SAID","ÁREA":"Proyectos","CARGO":"Jefe de Proyectos","GUARDIA":"C","Indicador":"INSPECCION","PROGRAMADO":"2","EJECUTADO":"1"},{"@odata.etag":"","ItemInternalId":"25e0f9b6-3ae2-4703-9a46-ffa1a0fa8032","Mes":"5","Año":"2026","DNI":"46578919","APELLIDOS Y NOMBRES":"PALACIOS ALDANA ARELIS","ÁREA":"Ssoma","CARGO":"Jefe de SSOMA","GUARDIA":"B","Indicador":"INSPECCION","PROGRAMADO":"2","EJECUTADO":"1"},{"@odata.etag":"","ItemInternalId":"350a3722-ae82-4d1e-8ac3-722867db83fd","Mes":"5","Año":"2026","DNI":"19968105","APELLIDOS Y NOMBRES":"SOTO MAPILCA WALTER","ÁREA":"Mantenimiento","CARGO":"Jefe Mantenimiento Mecanico","GUARDIA":"B","Indicador":"INSPECCION","PROGRAMADO":"2","EJECUTADO":"2"},{"@odata.etag":"","ItemInternalId":"000d482a-049c-4c44-966d-20b5c5ecfefb","Mes":"5","Año":"2026","DNI":"42075790","APELLIDOS Y NOMBRES":"RADAS PESANTES DANIEL","ÁREA":"Ssoma","CARGO":"Medico Ocupacional","GUARDIA":"C","Indicador":"INSPECCION","PROGRAMADO":"2","EJECUTADO":"2"},{"@odata.etag":"","ItemInternalId":"4b8d09d9-7882-4352-bc6b-307f54f32bd9","Mes":"5","Año":"2026","DNI":"40563190","APELLIDOS Y NOMBRES":"ALVAREZ ALVAREZ VICTOR","ÁREA":"Superintendencia","CARGO":"Superintendente de Planta","GUARDIA":"A","Indicador":"INSPECCION","PROGRAMADO":"2","EJECUTADO":"2"},{"@odata.etag":"","ItemInternalId":"d8b2c6fd-07a5-4917-9886-ec73300de353","Mes":"5","Año":"2026","DNI":"73099740","APELLIDOS Y NOMBRES":"UNTIVEROS HUANAY DERLIS","ÁREA":"Almacén","CARGO":"Supervisor Almacen","GUARDIA":"B","Indicador":"INSPECCION","PROGRAMADO":"2","EJECUTADO":"2"},{"@odata.etag":"","ItemInternalId":"cf17eb66-7fd9-46d2-ac7d-12b3dff4d291","Mes":"5","Año":"2026","DNI":"70521440","APELLIDOS Y NOMBRES":"BERROSPI BORDA CRISTIAN JACOB","ÁREA":"Laboratorio","CARGO":"Supervisor de Laboratorio","GUARDIA":"A","Indicador":"INSPECCION","PROGRAMADO":"1","EJECUTADO":"1"},{"@odata.etag":"","ItemInternalId":"33bf36f6-b2a5-4a16-ba9c-e5c1077dfcfa","Mes":"5","Año":"2026","DNI":"8684110","APELLIDOS Y NOMBRES":"MC INTOSH CANUT DE BON THOMAS NEIL","ÁREA":"Laboratorio","CARGO":"Supervisor de Laboratorio","GUARDIA":"A","Indicador":"INSPECCION","PROGRAMADO":"1","EJECUTADO":"1"},{"@odata.etag":"","ItemInternalId":"aac3af99-cce8-48f9-b74b-1d5beb49d60e","Mes":"5","Año":"2026","DNI":"75195592","APELLIDOS Y NOMBRES":"RIOS CHIPANA LUBALIE LESSLIE","ÁREA":"Laboratorio","CARGO":"Supervisor de Laboratorio","GUARDIA":"SG","Indicador":"INSPECCION","PROGRAMADO":"1","EJECUTADO":"2"},{"@odata.etag":"","ItemInternalId":"2bb37a01-f20c-4311-a125-2723bf4ff24c","Mes":"5","Año":"2026","DNI":"47940640","APELLIDOS Y NOMBRES":"VALENTIN MEZA ELVIS","ÁREA":"Proyectos","CARGO":"Supervisor de Obras Civiles","GUARDIA":"C","Indicador":"INSPECCION","PROGRAMADO":"1","EJECUTADO":"1"},{"@odata.etag":"","ItemInternalId":"524aea8a-a59e-4d86-912e-718f23776114","Mes":"5","Año":"2026","DNI":"44685748","APELLIDOS Y NOMBRES":"CONTRERAS PAREDES CESAR CLAUDIO","ÁREA":"Ssoma","CARGO":"Supervisor Ssoma","GUARDIA":"A","Indicador":"INSPECCION","PROGRAMADO":"1","EJECUTADO":"0"},{"@odata.etag":"","ItemInternalId":"f93225bd-47d4-44a4-bc7b-73ffe8e8a805","Mes":"5","Año":"2026","DNI":"70295889","APELLIDOS Y NOMBRES":"PALOMINO HUARCAYA JIMMY JOSEPH","ÁREA":"Ssoma","CARGO":"Supervisor Ssoma","GUARDIA":"SG","Indicador":"INSPECCION","PROGRAMADO":"1","EJECUTADO":"1"},{"@odata.etag":"","ItemInternalId":"4dd8f4ba-ede7-46c3-9cca-6dd64e50ea4b","Mes":"5","Año":"2026","DNI":"71874067","APELLIDOS Y NOMBRES":"CHAVEZ LOBATO SHIRLEY","ÁREA":"Superintendencia","CARGO":"Supervisor Jr Control de Procesos","GUARDIA":"C","Indicador":"INSPECCION","PROGRAMADO":"1","EJECUTADO":"2"},{"@odata.etag":"","ItemInternalId":"56674e93-dd40-4738-b5a8-79c971ae2a38","Mes":"5","Año":"2026","DNI":"76600483","APELLIDOS Y NOMBRES":"TORRES SAAVEDRA ROMINA BELEN","ÁREA":"Superintendencia","CARGO":"Supervisor Jr Control de Procesos","GUARDIA":"B","Indicador":"INSPECCION","PROGRAMADO":"1","EJECUTADO":"1"},{"@odata.etag":"","ItemInternalId":"af0dcd6f-9fa7-4a54-9675-7e95d258032e","Mes":"5","Año":"2026","DNI":"72405187","APELLIDOS Y NOMBRES":"CHIPANA VEGA ERICK STEVEN","ÁREA":"Proyectos","CARGO":"Supervisor de Obras Civiles","GUARDIA":"A","Indicador":"INSPECCION","PROGRAMADO":"1","EJECUTADO":"1"},{"@odata.etag":"","ItemInternalId":"508aa567-ad0f-43a8-be67-55ee2ca2ee1a","Mes":"5","Año":"2026","DNI":"73002062","APELLIDOS Y NOMBRES":"AMARO RAFAEL ADRIANA ANGELA","ÁREA":"Ssoma","CARGO":"Supervisor Ssoma","GUARDIA":"B","Indicador":"INSPECCION","PROGRAMADO":"1","EJECUTADO":"1"},{"@odata.etag":"","ItemInternalId":"eeeba409-b59d-4f3b-a8d9-6978b47cca18","Mes":"5","Año":"2026","DNI":"75350041","APELLIDOS Y NOMBRES":"OCHOA LEON JOSSELYN","ÁREA":"Superintendencia","CARGO":"Supervisor Control de Procesos","GUARDIA":"A","Indicador":"INSPECCION","PROGRAMADO":"1","EJECUTADO":"1"},{"@odata.etag":"","ItemInternalId":"4f803140-0462-469a-b869-125697cf87bb","Mes":"5","Año":"2026","DNI":"74589085","APELLIDOS Y NOMBRES":"FUENTES-DAVILA QUELOPANA MAURICIO","ÁREA":"Administración","CARGO":"Administrador","GUARDIA":"B","Indicador":"DDS","PROGRAMADO":"3","EJECUTADO":"2"},{"@odata.etag":"","ItemInternalId":"83d21389-e752-4d22-948b-9c3680d03879","Mes":"5","Año":"2026","DNI":"45789632","APELLIDOS Y NOMBRES":"CARRASCO JARAMILLO NATALIA","ÁREA":"Bienestar Social","CARGO":"Bienestar Social","GUARDIA":"B","Indicador":"DDS","PROGRAMADO":"3","EJECUTADO":"2"},{"@odata.etag":"","ItemInternalId":"9e507d9b-518c-4d3a-a52f-fecaea3314b0","Mes":"5","Año":"2026","DNI":"48556725","APELLIDOS Y NOMBRES":"GARCIA LAVADO ABEL","ÁREA":"Operaciones","CARGO":"Jefe de Guardia","GUARDIA":"C","Indicador":"DDS","PROGRAMADO":"3","EJECUTADO":"3"},{"@odata.etag":"","ItemInternalId":"f7374e1f-2ed7-4e08-8178-111981cc1d98","Mes":"5","Año":"2026","DNI":"44359932","APELLIDOS Y NOMBRES":"VARGAS CASTRO MIGUEL","ÁREA":"Operaciones","CARGO":"Jefe de Guardia","GUARDIA":"B","Indicador":"DDS","PROGRAMADO":"3","EJECUTADO":"3"},{"@odata.etag":"","ItemInternalId":"6a44d408-bc4e-4b84-83e1-d7d2bfd0563a","Mes":"5","Año":"2026","DNI":"44872088","APELLIDOS Y NOMBRES":"PACHECO HIRAOKA WILMER","ÁREA":"Operaciones","CARGO":"Jefe de Guardia","GUARDIA":"A","Indicador":"DDS","PROGRAMADO":"3","EJECUTADO":"3"},{"@odata.etag":"","ItemInternalId":"e583574b-022e-47e9-bea6-8fce544a04ba","Mes":"5","Año":"2026","DNI":"46336044","APELLIDOS Y NOMBRES":"ACUÑA QUISPE DAYGURO","ÁREA":"Laboratorio","CARGO":"Jefe de Laboratorio Quimico","GUARDIA":"B","Indicador":"DDS","PROGRAMADO":"3","EJECUTADO":"1"},{"@odata.etag":"","ItemInternalId":"fe5ed493-cc69-43fd-883c-590c1a83d562","Mes":"5","Año":"2026","DNI":"18144216","APELLIDOS Y NOMBRES":"CELIO RAMIREZ ANTONIO","ÁREA":"Mantenimiento","CARGO":"Jefe de Mantenimiento Electrico","GUARDIA":"C","Indicador":"DDS","PROGRAMADO":"3","EJECUTADO":"3"},{"@odata.etag":"","ItemInternalId":"b1f263c6-3dd6-4f12-a46a-048f1f7978d2","Mes":"5","Año":"2026","DNI":"70086433","APELLIDOS Y NOMBRES":"VEGA CASIANO ROMULO","ÁREA":"Mantenimiento","CARGO":"Jefe de Mantenimiento Vehicular","GUARDIA":"C","Indicador":"DDS","PROGRAMADO":"3","EJECUTADO":"3"},{"@odata.etag":"","ItemInternalId":"a877dc80-8061-4ef9-9dbe-254acc40e298","Mes":"5","Año":"2026","DNI":"77675654","APELLIDOS Y NOMBRES":"GORDILLO VELASQUES CRISTPHER","ÁREA":"Metalurgia","CARGO":"Jefe de Metalurgia","GUARDIA":"B","Indicador":"DDS","PROGRAMADO":"0","EJECUTADO":"0"},{"@odata.etag":"","ItemInternalId":"574b069b-23c3-471c-8cc4-9cc62cb1987a","Mes":"5","Año":"2026","DNI":"70458908","APELLIDOS Y NOMBRES":"PONCIANO JUSTO JOHNNY","ÁREA":"Producción","CARGO":"Jefe de Planta","GUARDIA":"B","Indicador":"DDS","PROGRAMADO":"3","EJECUTADO":"2"},{"@odata.etag":"","ItemInternalId":"2e4b732f-a907-44d6-80dd-2edc0d8b3347","Mes":"5","Año":"2026","DNI":"46660606","APELLIDOS Y NOMBRES":"GOMEZ ROSAS SAID","ÁREA":"Proyectos","CARGO":"Jefe de Proyectos","GUARDIA":"C","Indicador":"DDS","PROGRAMADO":"3","EJECUTADO":"3"},{"@odata.etag":"","ItemInternalId":"ed8578a1-8af8-418c-bb69-cc5e325210d5","Mes":"5","Año":"2026","DNI":"46578919","APELLIDOS Y NOMBRES":"PALACIOS ALDANA ARELIS","ÁREA":"Ssoma","CARGO":"Jefe de SSOMA","GUARDIA":"B","Indicador":"DDS","PROGRAMADO":"3","EJECUTADO":"3"},{"@odata.etag":"","ItemInternalId":"8e88732c-a474-4ff6-9813-65e81e233b7c","Mes":"5","Año":"2026","DNI":"19968105","APELLIDOS Y NOMBRES":"SOTO MAPILCA WALTER","ÁREA":"Mantenimiento","CARGO":"Jefe Mantenimiento Mecanico","GUARDIA":"B","Indicador":"DDS","PROGRAMADO":"3","EJECUTADO":"3"},{"@odata.etag":"","ItemInternalId":"faef0743-09f4-478c-a603-bafc54f00ff0","Mes":"5","Año":"2026","DNI":"42075790","APELLIDOS Y NOMBRES":"RADAS PESANTES DANIEL","ÁREA":"Ssoma","CARGO":"Medico Ocupacional","GUARDIA":"C","Indicador":"DDS","PROGRAMADO":"3","EJECUTADO":"3"},{"@odata.etag":"","ItemInternalId":"8d112add-41b0-4092-b743-766926e017e3","Mes":"5","Año":"2026","DNI":"40563190","APELLIDOS Y NOMBRES":"ALVAREZ ALVAREZ VICTOR","ÁREA":"Superintendencia","CARGO":"Superintendente de Planta","GUARDIA":"A","Indicador":"DDS","PROGRAMADO":"3","EJECUTADO":"0"},{"@odata.etag":"","ItemInternalId":"ccf85974-75e2-44ba-a652-b05cd87cd3e9","Mes":"5","Año":"2026","DNI":"73099740","APELLIDOS Y NOMBRES":"UNTIVEROS HUANAY DERLIS","ÁREA":"Almacén","CARGO":"Supervisor Almacen","GUARDIA":"B","Indicador":"DDS","PROGRAMADO":"3","EJECUTADO":"2"},{"@odata.etag":"","ItemInternalId":"20fe0760-fcd2-4cce-8c59-1fb2ac683d7b","Mes":"5","Año":"2026","DNI":"70521440","APELLIDOS Y NOMBRES":"BERROSPI BORDA CRISTIAN JACOB","ÁREA":"Laboratorio","CARGO":"Supervisor de Laboratorio","GUARDIA":"A","Indicador":"DDS","PROGRAMADO":"2","EJECUTADO":"2"},{"@odata.etag":"","ItemInternalId":"5e6ba07b-aba5-4d46-837a-9f71c60ebc8a","Mes":"5","Año":"2026","DNI":"8684110","APELLIDOS Y NOMBRES":"MC INTOSH CANUT DE BON THOMAS NEIL","ÁREA":"Laboratorio","CARGO":"Supervisor de Laboratorio","GUARDIA":"A","Indicador":"DDS","PROGRAMADO":"2","EJECUTADO":"1"},{"@odata.etag":"","ItemInternalId":"49712bfd-a550-42b6-bf62-8e76aff0734a","Mes":"5","Año":"2026","DNI":"75195592","APELLIDOS Y NOMBRES":"RIOS CHIPANA LUBALIE LESSLIE","ÁREA":"Laboratorio","CARGO":"Supervisor de Laboratorio","GUARDIA":"SG","Indicador":"DDS","PROGRAMADO":"2","EJECUTADO":"1"},{"@odata.etag":"","ItemInternalId":"a8a91a7d-9b6d-4d5b-b7f3-06ae11c83099","Mes":"5","Año":"2026","DNI":"47940640","APELLIDOS Y NOMBRES":"VALENTIN MEZA ELVIS","ÁREA":"Proyectos","CARGO":"Supervisor de Obras Civiles","GUARDIA":"C","Indicador":"DDS","PROGRAMADO":"2","EJECUTADO":"2"},{"@odata.etag":"","ItemInternalId":"8f7e7383-ad32-45a8-b996-8ce473d96401","Mes":"5","Año":"2026","DNI":"44685748","APELLIDOS Y NOMBRES":"CONTRERAS PAREDES CESAR CLAUDIO","ÁREA":"Ssoma","CARGO":"Supervisor Ssoma","GUARDIA":"A","Indicador":"DDS","PROGRAMADO":"2","EJECUTADO":"1"},{"@odata.etag":"","ItemInternalId":"60601063-16f3-417b-ad8b-093f8c9f7fb0","Mes":"5","Año":"2026","DNI":"70295889","APELLIDOS Y NOMBRES":"PALOMINO HUARCAYA JIMMY JOSEPH","ÁREA":"Ssoma","CARGO":"Supervisor Ssoma","GUARDIA":"SG","Indicador":"DDS","PROGRAMADO":"2","EJECUTADO":"2"},{"@odata.etag":"","ItemInternalId":"8abbb856-80fb-4bd3-b89b-c96f490c0f23","Mes":"5","Año":"2026","DNI":"71874067","APELLIDOS Y NOMBRES":"CHAVEZ LOBATO SHIRLEY","ÁREA":"Superintendencia","CARGO":"Supervisor Jr Control de Procesos","GUARDIA":"C","Indicador":"DDS","PROGRAMADO":"2","EJECUTADO":"2"},{"@odata.etag":"","ItemInternalId":"e5cf3c98-3597-48e9-b999-07c6ea1a53cc","Mes":"5","Año":"2026","DNI":"76600483","APELLIDOS Y NOMBRES":"TORRES SAAVEDRA ROMINA BELEN","ÁREA":"Superintendencia","CARGO":"Supervisor Jr Control de Procesos","GUARDIA":"B","Indicador":"DDS","PROGRAMADO":"2","EJECUTADO":"2"},{"@odata.etag":"","ItemInternalId":"81f76c44-9947-4a8f-9bcb-5608c32354b3","Mes":"5","Año":"2026","DNI":"72405187","APELLIDOS Y NOMBRES":"CHIPANA VEGA ERICK STEVEN","ÁREA":"Proyectos","CARGO":"Supervisor de Obras Civiles","GUARDIA":"A","Indicador":"DDS","PROGRAMADO":"2","EJECUTADO":"1"},{"@odata.etag":"","ItemInternalId":"9243e7c3-c1bd-4379-a1ac-88d7aa697537","Mes":"5","Año":"2026","DNI":"73002062","APELLIDOS Y NOMBRES":"AMARO RAFAEL ADRIANA ANGELA","ÁREA":"Ssoma","CARGO":"Supervisor Ssoma","GUARDIA":"B","Indicador":"DDS","PROGRAMADO":"2","EJECUTADO":"2"},{"@odata.etag":"","ItemInternalId":"90119bad-9bc6-4ff7-997e-01b9f2e64533","Mes":"5","Año":"2026","DNI":"75350041","APELLIDOS Y NOMBRES":"OCHOA LEON JOSSELYN","ÁREA":"Superintendencia","CARGO":"Supervisor Control de Procesos","GUARDIA":"A","Indicador":"DDS","PROGRAMADO":"2","EJECUTADO":"1"},{"@odata.etag":"","ItemInternalId":"efbaf815-1e1f-454e-8c53-9c9255f9fe69","Mes":"5","Año":"2026","DNI":"74589085","APELLIDOS Y NOMBRES":"FUENTES-DAVILA QUELOPANA MAURICIO","ÁREA":"Administración","CARGO":"Administrador","GUARDIA":"B","Indicador":"CAPACITACION SSO","PROGRAMADO":"1","EJECUTADO":"1"},{"@odata.etag":"","ItemInternalId":"1d7d1996-8870-4be2-80b2-fd7620b202a3","Mes":"5","Año":"2026","DNI":"45789632","APELLIDOS Y NOMBRES":"CARRASCO JARAMILLO NATALIA","ÁREA":"Bienestar Social","CARGO":"Bienestar Social","GUARDIA":"B","Indicador":"CAPACITACION SSO","PROGRAMADO":"1","EJECUTADO":"1"},{"@odata.etag":"","ItemInternalId":"6827ca40-7377-4822-9631-1cea34b45439","Mes":"5","Año":"2026","DNI":"48556725","APELLIDOS Y NOMBRES":"GARCIA LAVADO ABEL","ÁREA":"Operaciones","CARGO":"Jefe de Guardia","GUARDIA":"C","Indicador":"CAPACITACION SSO","PROGRAMADO":"1","EJECUTADO":"1"},{"@odata.etag":"","ItemInternalId":"f8e8979e-1d12-4c92-bb3c-712d8e0c93ff","Mes":"5","Año":"2026","DNI":"44359932","APELLIDOS Y NOMBRES":"VARGAS CASTRO MIGUEL","ÁREA":"Operaciones","CARGO":"Jefe de Guardia","GUARDIA":"B","Indicador":"CAPACITACION SSO","PROGRAMADO":"1","EJECUTADO":"0"},{"@odata.etag":"","ItemInternalId":"cd5a53a9-d466-4afb-8baa-bb0cfe9c9a5a","Mes":"5","Año":"2026","DNI":"44872088","APELLIDOS Y NOMBRES":"PACHECO HIRAOKA WILMER","ÁREA":"Operaciones","CARGO":"Jefe de Guardia","GUARDIA":"A","Indicador":"CAPACITACION SSO","PROGRAMADO":"1","EJECUTADO":"1"},{"@odata.etag":"","ItemInternalId":"21a1ea7b-7555-4a31-854c-29d66f8f9580","Mes":"5","Año":"2026","DNI":"46336044","APELLIDOS Y NOMBRES":"ACUÑA QUISPE DAYGURO","ÁREA":"Laboratorio","CARGO":"Jefe de Laboratorio Quimico","GUARDIA":"B","Indicador":"CAPACITACION SSO","PROGRAMADO":"1","EJECUTADO":"1"},{"@odata.etag":"","ItemInternalId":"c2ecc3fe-36a2-462d-9e7a-2fc18ac16b71","Mes":"5","Año":"2026","DNI":"18144216","APELLIDOS Y NOMBRES":"CELIO RAMIREZ ANTONIO","ÁREA":"Mantenimiento","CARGO":"Jefe de Mantenimiento Electrico","GUARDIA":"C","Indicador":"CAPACITACION SSO","PROGRAMADO":"1","EJECUTADO":"1"},{"@odata.etag":"","ItemInternalId":"c20251a4-de71-4440-a48e-c83ce79708b7","Mes":"5","Año":"2026","DNI":"70086433","APELLIDOS Y NOMBRES":"VEGA CASIANO ROMULO","ÁREA":"Mantenimiento","CARGO":"Jefe de Mantenimiento Vehicular","GUARDIA":"C","Indicador":"CAPACITACION SSO","PROGRAMADO":"1","EJECUTADO":"0"},{"@odata.etag":"","ItemInternalId":"6e1b7077-5c5b-48dc-bbd8-20f46f086e26","Mes":"5","Año":"2026","DNI":"77675654","APELLIDOS Y NOMBRES":"GORDILLO VELASQUES CRISTPHER","ÁREA":"Metalurgia","CARGO":"Jefe de Metalurgia","GUARDIA":"B","Indicador":"CAPACITACION SSO","PROGRAMADO":"0","EJECUTADO":"0"},{"@odata.etag":"","ItemInternalId":"21d7a5ec-62e2-494f-b09f-e76322154b15","Mes":"5","Año":"2026","DNI":"70458908","APELLIDOS Y NOMBRES":"PONCIANO JUSTO JOHNNY","ÁREA":"Producción","CARGO":"Jefe de Planta","GUARDIA":"B","Indicador":"CAPACITACION SSO","PROGRAMADO":"1","EJECUTADO":"1"},{"@odata.etag":"","ItemInternalId":"a865f58f-5bc2-4914-a4dd-01f0d051fe26","Mes":"5","Año":"2026","DNI":"46660606","APELLIDOS Y NOMBRES":"GOMEZ ROSAS SAID","ÁREA":"Proyectos","CARGO":"Jefe de Proyectos","GUARDIA":"C","Indicador":"CAPACITACION SSO","PROGRAMADO":"1","EJECUTADO":"1"},{"@odata.etag":"","ItemInternalId":"e9a873cb-5aaf-49f8-98ee-7844ef95ebad","Mes":"5","Año":"2026","DNI":"46578919","APELLIDOS Y NOMBRES":"PALACIOS ALDANA ARELIS","ÁREA":"Ssoma","CARGO":"Jefe de SSOMA","GUARDIA":"B","Indicador":"CAPACITACION SSO","PROGRAMADO":"1","EJECUTADO":"1"},{"@odata.etag":"","ItemInternalId":"b80ad9da-c257-4455-b7ec-d5e2459be329","Mes":"5","Año":"2026","DNI":"19968105","APELLIDOS Y NOMBRES":"SOTO MAPILCA WALTER","ÁREA":"Mantenimiento","CARGO":"Jefe Mantenimiento Mecanico","GUARDIA":"B","Indicador":"CAPACITACION SSO","PROGRAMADO":"1","EJECUTADO":"1"},{"@odata.etag":"","ItemInternalId":"7bdc94f2-420c-49c8-aba5-d602e760ee1b","Mes":"5","Año":"2026","DNI":"42075790","APELLIDOS Y NOMBRES":"RADAS PESANTES DANIEL","ÁREA":"Ssoma","CARGO":"Medico Ocupacional","GUARDIA":"C","Indicador":"CAPACITACION SSO","PROGRAMADO":"1","EJECUTADO":"1"},{"@odata.etag":"","ItemInternalId":"7f2c34f1-0a84-41e3-b50c-5eb1e5dffba3","Mes":"5","Año":"2026","DNI":"40563190","APELLIDOS Y NOMBRES":"ALVAREZ ALVAREZ VICTOR","ÁREA":"Superintendencia","CARGO":"Superintendente de Planta","GUARDIA":"A","Indicador":"CAPACITACION SSO","PROGRAMADO":"1","EJECUTADO":"1"},{"@odata.etag":"","ItemInternalId":"6702ff6c-864a-463e-a76e-88b2767ede12","Mes":"5","Año":"2026","DNI":"73099740","APELLIDOS Y NOMBRES":"UNTIVEROS HUANAY DERLIS","ÁREA":"Almacén","CARGO":"Supervisor Almacen","GUARDIA":"B","Indicador":"CAPACITACION SSO","PROGRAMADO":"1","EJECUTADO":"0"},{"@odata.etag":"","ItemInternalId":"ff26ba80-6593-41c6-8c42-82899f306f51","Mes":"5","Año":"2026","DNI":"70521440","APELLIDOS Y NOMBRES":"BERROSPI BORDA CRISTIAN JACOB","ÁREA":"Laboratorio","CARGO":"Supervisor de Laboratorio","GUARDIA":"A","Indicador":"CAPACITACION SSO","PROGRAMADO":"0","EJECUTADO":"0"},{"@odata.etag":"","ItemInternalId":"a7feddbe-d3cc-4d5e-8cda-c69dd12f96bf","Mes":"5","Año":"2026","DNI":"8684110","APELLIDOS Y NOMBRES":"MC INTOSH CANUT DE BON THOMAS NEIL","ÁREA":"Laboratorio","CARGO":"Supervisor de Laboratorio","GUARDIA":"A","Indicador":"CAPACITACION SSO","PROGRAMADO":"0","EJECUTADO":"0"},{"@odata.etag":"","ItemInternalId":"994b47c3-094e-4163-a32e-0cff96b4cc55","Mes":"5","Año":"2026","DNI":"75195592","APELLIDOS Y NOMBRES":"RIOS CHIPANA LUBALIE LESSLIE","ÁREA":"Laboratorio","CARGO":"Supervisor de Laboratorio","GUARDIA":"SG","Indicador":"CAPACITACION SSO","PROGRAMADO":"0","EJECUTADO":"0"},{"@odata.etag":"","ItemInternalId":"883a49ab-cf95-4c69-a264-d3bb2cd9306e","Mes":"5","Año":"2026","DNI":"47940640","APELLIDOS Y NOMBRES":"VALENTIN MEZA ELVIS","ÁREA":"Proyectos","CARGO":"Supervisor de Obras Civiles","GUARDIA":"C","Indicador":"CAPACITACION SSO","PROGRAMADO":"0","EJECUTADO":"0"},{"@odata.etag":"","ItemInternalId":"21f898ab-8c9b-45be-8198-24c40d3b9709","Mes":"5","Año":"2026","DNI":"44685748","APELLIDOS Y NOMBRES":"CONTRERAS PAREDES CESAR CLAUDIO","ÁREA":"Ssoma","CARGO":"Supervisor Ssoma","GUARDIA":"A","Indicador":"CAPACITACION SSO","PROGRAMADO":"0","EJECUTADO":"0"},{"@odata.etag":"","ItemInternalId":"7421f1c4-1f6a-4dfc-b1a9-49ed751b9975","Mes":"5","Año":"2026","DNI":"70295889","APELLIDOS Y NOMBRES":"PALOMINO HUARCAYA JIMMY JOSEPH","ÁREA":"Ssoma","CARGO":"Supervisor Ssoma","GUARDIA":"SG","Indicador":"CAPACITACION SSO","PROGRAMADO":"0","EJECUTADO":"0"},{"@odata.etag":"","ItemInternalId":"586f5879-0946-4fea-8fe1-078ac30b196e","Mes":"5","Año":"2026","DNI":"71874067","APELLIDOS Y NOMBRES":"CHAVEZ LOBATO SHIRLEY","ÁREA":"Superintendencia","CARGO":"Supervisor Jr Control de Procesos","GUARDIA":"C","Indicador":"CAPACITACION SSO","PROGRAMADO":"0","EJECUTADO":"0"},{"@odata.etag":"","ItemInternalId":"ddda394b-80c4-4a9f-b3c1-4213ad9ac71e","Mes":"5","Año":"2026","DNI":"76600483","APELLIDOS Y NOMBRES":"TORRES SAAVEDRA ROMINA BELEN","ÁREA":"Superintendencia","CARGO":"Supervisor Jr Control de Procesos","GUARDIA":"B","Indicador":"CAPACITACION SSO","PROGRAMADO":"0","EJECUTADO":"0"},{"@odata.etag":"","ItemInternalId":"25b650dd-44e9-4a77-beae-61f74d5e6369","Mes":"5","Año":"2026","DNI":"72405187","APELLIDOS Y NOMBRES":"CHIPANA VEGA ERICK STEVEN","ÁREA":"Proyectos","CARGO":"Supervisor de Obras Civiles","GUARDIA":"A","Indicador":"CAPACITACION SSO","PROGRAMADO":"0","EJECUTADO":"0"},{"@odata.etag":"","ItemInternalId":"248c3539-4c6d-4894-bd4d-ba32e0c161f3","Mes":"5","Año":"2026","DNI":"73002062","APELLIDOS Y NOMBRES":"AMARO RAFAEL ADRIANA ANGELA","ÁREA":"Ssoma","CARGO":"Supervisor Ssoma","GUARDIA":"B","Indicador":"CAPACITACION SSO","PROGRAMADO":"0","EJECUTADO":"0"},{"@odata.etag":"","ItemInternalId":"ecad6a3d-2a95-4a87-b9b9-f25c2c5d9931","Mes":"5","Año":"2026","DNI":"75350041","APELLIDOS Y NOMBRES":"OCHOA LEON JOSSELYN","ÁREA":"Superintendencia","CARGO":"Supervisor Control de Procesos","GUARDIA":"A","Indicador":"CAPACITACION SSO","PROGRAMADO":"0","EJECUTADO":"0"},{"@odata.etag":"","ItemInternalId":"e7b3265b-4b59-4c7d-b7a8-d9bc256d5b95","Mes":"5","Año":"2026","DNI":"74589085","APELLIDOS Y NOMBRES":"FUENTES-DAVILA QUELOPANA MAURICIO","ÁREA":"Administración","CARGO":"Administrador","GUARDIA":"B","Indicador":"RACs","PROGRAMADO":"3","EJECUTADO":"3"},{"@odata.etag":"","ItemInternalId":"29605caf-9d17-4578-bcd4-be571b949308","Mes":"5","Año":"2026","DNI":"45789632","APELLIDOS Y NOMBRES":"CARRASCO JARAMILLO NATALIA","ÁREA":"Bienestar Social","CARGO":"Bienestar Social","GUARDIA":"B","Indicador":"RACs","PROGRAMADO":"3","EJECUTADO":"4"},{"@odata.etag":"","ItemInternalId":"86c995f0-dc74-4863-a3f4-02599f3abf29","Mes":"5","Año":"2026","DNI":"48556725","APELLIDOS Y NOMBRES":"GARCIA LAVADO ABEL","ÁREA":"Operaciones","CARGO":"Jefe de Guardia","GUARDIA":"C","Indicador":"RACs","PROGRAMADO":"3","EJECUTADO":"4"},{"@odata.etag":"","ItemInternalId":"c522ab9d-59a5-4ed0-8872-e514ef6220f0","Mes":"5","Año":"2026","DNI":"44359932","APELLIDOS Y NOMBRES":"VARGAS CASTRO MIGUEL","ÁREA":"Operaciones","CARGO":"Jefe de Guardia","GUARDIA":"B","Indicador":"RACs","PROGRAMADO":"3","EJECUTADO":"3"},{"@odata.etag":"","ItemInternalId":"77533803-e763-4e74-b80a-e494686c9fba","Mes":"5","Año":"2026","DNI":"44872088","APELLIDOS Y NOMBRES":"PACHECO HIRAOKA WILMER","ÁREA":"Operaciones","CARGO":"Jefe de Guardia","GUARDIA":"A","Indicador":"RACs","PROGRAMADO":"3","EJECUTADO":"3"},{"@odata.etag":"","ItemInternalId":"de80d223-78af-438b-a996-0338c39482ba","Mes":"5","Año":"2026","DNI":"46336044","APELLIDOS Y NOMBRES":"ACUÑA QUISPE DAYGURO","ÁREA":"Laboratorio","CARGO":"Jefe de Laboratorio Quimico","GUARDIA":"B","Indicador":"RACs","PROGRAMADO":"3","EJECUTADO":"1"},{"@odata.etag":"","ItemInternalId":"ec6b8c16-af8a-4cf7-9ca1-6e2659b972c3","Mes":"5","Año":"2026","DNI":"18144216","APELLIDOS Y NOMBRES":"CELIO RAMIREZ ANTONIO","ÁREA":"Mantenimiento","CARGO":"Jefe de Mantenimiento Electrico","GUARDIA":"C","Indicador":"RACs","PROGRAMADO":"3","EJECUTADO":"6"},{"@odata.etag":"","ItemInternalId":"d4849c97-573a-4d9c-8217-5b6c590c8191","Mes":"5","Año":"2026","DNI":"70086433","APELLIDOS Y NOMBRES":"VEGA CASIANO ROMULO","ÁREA":"Mantenimiento","CARGO":"Jefe de Mantenimiento Vehicular","GUARDIA":"C","Indicador":"RACs","PROGRAMADO":"3","EJECUTADO":"3"},{"@odata.etag":"","ItemInternalId":"69fd155f-527b-4c7e-b885-e315ff80a413","Mes":"5","Año":"2026","DNI":"77675654","APELLIDOS Y NOMBRES":"GORDILLO VELASQUES CRISTPHER","ÁREA":"Metalurgia","CARGO":"Jefe de Metalurgia","GUARDIA":"B","Indicador":"RACs","PROGRAMADO":"0","EJECUTADO":"0"},{"@odata.etag":"","ItemInternalId":"c620edef-b05d-42a7-9175-94162ffbb5e7","Mes":"5","Año":"2026","DNI":"70458908","APELLIDOS Y NOMBRES":"PONCIANO JUSTO JOHNNY","ÁREA":"Producción","CARGO":"Jefe de Planta","GUARDIA":"B","Indicador":"RACs","PROGRAMADO":"3","EJECUTADO":"4"},{"@odata.etag":"","ItemInternalId":"7c65c635-066b-469e-965d-42572fbb7daa","Mes":"5","Año":"2026","DNI":"46660606","APELLIDOS Y NOMBRES":"GOMEZ ROSAS SAID","ÁREA":"Proyectos","CARGO":"Jefe de Proyectos","GUARDIA":"C","Indicador":"RACs","PROGRAMADO":"3","EJECUTADO":"3"},{"@odata.etag":"","ItemInternalId":"6d048686-79b0-40b2-b89f-e8ea0d7725b9","Mes":"5","Año":"2026","DNI":"46578919","APELLIDOS Y NOMBRES":"PALACIOS ALDANA ARELIS","ÁREA":"Ssoma","CARGO":"Jefe de SSOMA","GUARDIA":"B","Indicador":"RACs","PROGRAMADO":"3","EJECUTADO":"3"},{"@odata.etag":"","ItemInternalId":"d39f8e9c-8c6b-45bd-b013-579f02093528","Mes":"5","Año":"2026","DNI":"19968105","APELLIDOS Y NOMBRES":"SOTO MAPILCA WALTER","ÁREA":"Mantenimiento","CARGO":"Jefe Mantenimiento Mecanico","GUARDIA":"B","Indicador":"RACs","PROGRAMADO":"3","EJECUTADO":"4"},{"@odata.etag":"","ItemInternalId":"0b998be6-7846-4143-a8e8-253bfe915416","Mes":"5","Año":"2026","DNI":"42075790","APELLIDOS Y NOMBRES":"RADAS PESANTES DANIEL","ÁREA":"Ssoma","CARGO":"Medico Ocupacional","GUARDIA":"C","Indicador":"RACs","PROGRAMADO":"3","EJECUTADO":"3"},{"@odata.etag":"","ItemInternalId":"bd50fa54-ce9d-4cab-b561-502df6b062e1","Mes":"5","Año":"2026","DNI":"40563190","APELLIDOS Y NOMBRES":"ALVAREZ ALVAREZ VICTOR","ÁREA":"Superintendencia","CARGO":"Superintendente de Planta","GUARDIA":"A","Indicador":"RACs","PROGRAMADO":"3","EJECUTADO":"4"},{"@odata.etag":"","ItemInternalId":"9a220b54-f9b9-4bb6-9ccf-dc3a529589d4","Mes":"5","Año":"2026","DNI":"73099740","APELLIDOS Y NOMBRES":"UNTIVEROS HUANAY DERLIS","ÁREA":"Almacén","CARGO":"Supervisor Almacen","GUARDIA":"B","Indicador":"RACs","PROGRAMADO":"3","EJECUTADO":"7"},{"@odata.etag":"","ItemInternalId":"4c148780-bf1c-4032-a3e4-c128dd32bcd6","Mes":"5","Año":"2026","DNI":"70521440","APELLIDOS Y NOMBRES":"BERROSPI BORDA CRISTIAN JACOB","ÁREA":"Laboratorio","CARGO":"Supervisor de Laboratorio","GUARDIA":"A","Indicador":"RACs","PROGRAMADO":"2","EJECUTADO":"3"},{"@odata.etag":"","ItemInternalId":"a7848a9a-5170-4d22-b21e-ad9ea5543ef8","Mes":"5","Año":"2026","DNI":"8684110","APELLIDOS Y NOMBRES":"MC INTOSH CANUT DE BON THOMAS NEIL","ÁREA":"Laboratorio","CARGO":"Supervisor de Laboratorio","GUARDIA":"A","Indicador":"RACs","PROGRAMADO":"2","EJECUTADO":"2"},{"@odata.etag":"","ItemInternalId":"495f4ca1-6060-4a24-90c5-3436d357b51a","Mes":"5","Año":"2026","DNI":"75195592","APELLIDOS Y NOMBRES":"RIOS CHIPANA LUBALIE LESSLIE","ÁREA":"Laboratorio","CARGO":"Supervisor de Laboratorio","GUARDIA":"SG","Indicador":"RACs","PROGRAMADO":"2","EJECUTADO":"3"},{"@odata.etag":"","ItemInternalId":"310faa77-f7e3-4d49-bfbb-9427a1821897","Mes":"5","Año":"2026","DNI":"47940640","APELLIDOS Y NOMBRES":"VALENTIN MEZA ELVIS","ÁREA":"Proyectos","CARGO":"Supervisor de Obras Civiles","GUARDIA":"C","Indicador":"RACs","PROGRAMADO":"2","EJECUTADO":"2"},{"@odata.etag":"","ItemInternalId":"d3cfb43d-a974-4e63-b110-c49543fc9d6a","Mes":"5","Año":"2026","DNI":"44685748","APELLIDOS Y NOMBRES":"CONTRERAS PAREDES CESAR CLAUDIO","ÁREA":"Ssoma","CARGO":"Supervisor Ssoma","GUARDIA":"A","Indicador":"RACs","PROGRAMADO":"2","EJECUTADO":"3"},{"@odata.etag":"","ItemInternalId":"6e25db4e-d4f9-4f1c-89e7-47c06a15bd91","Mes":"5","Año":"2026","DNI":"70295889","APELLIDOS Y NOMBRES":"PALOMINO HUARCAYA JIMMY JOSEPH","ÁREA":"Ssoma","CARGO":"Supervisor Ssoma","GUARDIA":"SG","Indicador":"RACs","PROGRAMADO":"2","EJECUTADO":"2"},{"@odata.etag":"","ItemInternalId":"403e09e8-960c-44f8-9d19-7d7841e11d34","Mes":"5","Año":"2026","DNI":"71874067","APELLIDOS Y NOMBRES":"CHAVEZ LOBATO SHIRLEY","ÁREA":"Superintendencia","CARGO":"Supervisor Jr Control de Procesos","GUARDIA":"C","Indicador":"RACs","PROGRAMADO":"2","EJECUTADO":"2"},{"@odata.etag":"","ItemInternalId":"41b5d5b0-f83b-4129-8acf-f3971b39ee44","Mes":"5","Año":"2026","DNI":"76600483","APELLIDOS Y NOMBRES":"TORRES SAAVEDRA ROMINA BELEN","ÁREA":"Superintendencia","CARGO":"Supervisor Jr Control de Procesos","GUARDIA":"B","Indicador":"RACs","PROGRAMADO":"2","EJECUTADO":"11"},{"@odata.etag":"","ItemInternalId":"ca7636df-d444-4c6b-b7f8-c78f0ba31c8e","Mes":"5","Año":"2026","DNI":"72405187","APELLIDOS Y NOMBRES":"CHIPANA VEGA ERICK STEVEN","ÁREA":"Proyectos","CARGO":"Supervisor de Obras Civiles","GUARDIA":"A","Indicador":"RACs","PROGRAMADO":"2","EJECUTADO":"3"},{"@odata.etag":"","ItemInternalId":"b9021e62-3322-4f5c-858d-d9de092b11be","Mes":"5","Año":"2026","DNI":"73002062","APELLIDOS Y NOMBRES":"AMARO RAFAEL ADRIANA ANGELA","ÁREA":"Ssoma","CARGO":"Supervisor Ssoma","GUARDIA":"B","Indicador":"RACs","PROGRAMADO":"2","EJECUTADO":"3"},{"@odata.etag":"","ItemInternalId":"150100a3-8d56-43f0-a83c-47fb1db9a45d","Mes":"5","Año":"2026","DNI":"75350041","APELLIDOS Y NOMBRES":"OCHOA LEON JOSSELYN","ÁREA":"Superintendencia","CARGO":"Supervisor Control de Procesos","GUARDIA":"A","Indicador":"RACs","PROGRAMADO":"2","EJECUTADO":"2"},{"@odata.etag":"","ItemInternalId":"9fa3d596-8fe3-4991-ba70-2cf5ae6fe57a","Mes":"4","Año":"2026","DNI":"40563190","APELLIDOS Y NOMBRES":"ALVAREZ ALVAREZ VICTOR","ÁREA":"Superintendencia","CARGO":"Superintendente de Planta","GUARDIA":"A","Indicador":"INSPECCION","PROGRAMADO":"2","EJECUTADO":"2"},{"@odata.etag":"","ItemInternalId":"0036a289-c34c-4c5f-bb1a-8971e6b287dd","Mes":"4","Año":"2026","DNI":"70458908","APELLIDOS Y NOMBRES":"PONCIANO JUSTO JOHNNY","ÁREA":"Producción","CARGO":"Jefe de Planta","GUARDIA":"B","Indicador":"INSPECCION","PROGRAMADO":"2","EJECUTADO":"2"},{"@odata.etag":"","ItemInternalId":"386f901c-36c6-4362-b3c2-baec7a782611","Mes":"4","Año":"2026","DNI":"46578919","APELLIDOS Y NOMBRES":"PALACIOS ALDANA ARELIS","ÁREA":"Ssoma","CARGO":"Jefe de SSOMA","GUARDIA":"B","Indicador":"INSPECCION","PROGRAMADO":"2","EJECUTADO":"2"},{"@odata.etag":"","ItemInternalId":"4b0825c4-64ad-470a-b167-c207ec0e0964","Mes":"4","Año":"2026","DNI":"48556725","APELLIDOS Y NOMBRES":"GARCIA LAVADO ABEL","ÁREA":"Operaciones","CARGO":"Jefe de Guardia","GUARDIA":"C","Indicador":"INSPECCION","PROGRAMADO":"2","EJECUTADO":"2"},{"@odata.etag":"","ItemInternalId":"893230f5-8627-4151-b3ac-4238df79f491","Mes":"4","Año":"2026","DNI":"44359932","APELLIDOS Y NOMBRES":"VARGAS CASTRO MIGUEL","ÁREA":"Operaciones","CARGO":"Jefe de Guardia","GUARDIA":"B","Indicador":"INSPECCION","PROGRAMADO":"2","EJECUTADO":"2"},{"@odata.etag":"","ItemInternalId":"7129510b-b520-44ce-b230-86aad9010b98","Mes":"4","Año":"2026","DNI":"44872088","APELLIDOS Y NOMBRES":"PACHECO HIRAOKA WILMER","ÁREA":"Operaciones","CARGO":"Jefe de Guardia","GUARDIA":"A","Indicador":"INSPECCION","PROGRAMADO":"2","EJECUTADO":"2"},{"@odata.etag":"","ItemInternalId":"5215191f-2f1f-4260-b8db-c6b8175165b3","Mes":"4","Año":"2026","DNI":"19968105","APELLIDOS Y NOMBRES":"SOTO MAPILCA WALTER","ÁREA":"Mantenimiento","CARGO":"Jefe Mantenimiento Mecanico","GUARDIA":"B","Indicador":"INSPECCION","PROGRAMADO":"2","EJECUTADO":"2"},{"@odata.etag":"","ItemInternalId":"24107464-49a3-4396-b920-b435d6e342ac","Mes":"4","Año":"2026","DNI":"18144216","APELLIDOS Y NOMBRES":"CELIO RAMIREZ ANTONIO","ÁREA":"Mantenimiento","CARGO":"Jefe de Mantenimiento Electrico","GUARDIA":"C","Indicador":"INSPECCION","PROGRAMADO":"2","EJECUTADO":"2"},{"@odata.etag":"","ItemInternalId":"8bcd275b-ed8f-4721-ad2d-05784f3db974","Mes":"4","Año":"2026","DNI":"70086433","APELLIDOS Y NOMBRES":"VEGA CASIANO ROMULO","ÁREA":"Mantenimiento","CARGO":"Jefe de Mantenimiento Vehicular","GUARDIA":"C","Indicador":"INSPECCION","PROGRAMADO":"2","EJECUTADO":"2"},{"@odata.etag":"","ItemInternalId":"d5fdf0f1-5f51-41bd-bf3e-d4640f4cb45c","Mes":"4","Año":"2026","DNI":"77675654","APELLIDOS Y NOMBRES":"GORDILLO VELASQUES CRISTPHER","ÁREA":"Metalurgia","CARGO":"Jefe de Metalurgia","GUARDIA":"B","Indicador":"INSPECCION","PROGRAMADO":"2","EJECUTADO":"2"},{"@odata.etag":"","ItemInternalId":"6b7e8988-5235-433c-bdb6-0a094daccf0e","Mes":"4","Año":"2026","DNI":"46660606","APELLIDOS Y NOMBRES":"GOMEZ ROSAS SAID","ÁREA":"Proyectos","CARGO":"Jefe de Proyectos","GUARDIA":"C","Indicador":"INSPECCION","PROGRAMADO":"2","EJECUTADO":"2"},{"@odata.etag":"","ItemInternalId":"5443c117-fb46-41e6-b6b7-d3725aed202e","Mes":"4","Año":"2026","DNI":"74589085","APELLIDOS Y NOMBRES":"FUENTES-DAVILA QUELOPANA MAURICIO","ÁREA":"Administración","CARGO":"Administrador","GUARDIA":"B","Indicador":"INSPECCION","PROGRAMADO":"2","EJECUTADO":"2"},{"@odata.etag":"","ItemInternalId":"9e9105e5-186d-4be5-b4ea-3799d2db2128","Mes":"4","Año":"2026","DNI":"46336044","APELLIDOS Y NOMBRES":"ACUÑA QUISPE DAYGURO","ÁREA":"Laboratorio","CARGO":"Jefe de Laboratorio Quimico","GUARDIA":"B","Indicador":"INSPECCION","PROGRAMADO":"2","EJECUTADO":"2"},{"@odata.etag":"","ItemInternalId":"d9b9b838-7478-4843-9ad8-4afd522f2482","Mes":"4","Año":"2026","DNI":"45789632","APELLIDOS Y NOMBRES":"CARRASCO JARAMILLO NATALIA","ÁREA":"Bienestar Social","CARGO":"Bienestar Social","GUARDIA":"B","Indicador":"INSPECCION","PROGRAMADO":"2","EJECUTADO":"2"},{"@odata.etag":"","ItemInternalId":"c5e55edf-693f-4a5a-be70-1e3c9ad08fa8","Mes":"4","Año":"2026","DNI":"73099740","APELLIDOS Y NOMBRES":"UNTIVEROS HUANAY DERLIS","ÁREA":"Almacén","CARGO":"Supervisor Almacen","GUARDIA":"B","Indicador":"INSPECCION","PROGRAMADO":"2","EJECUTADO":"2"},{"@odata.etag":"","ItemInternalId":"9f2850cb-54f8-40a5-8ed4-c585f5f68406","Mes":"4","Año":"2026","DNI":"42075790","APELLIDOS Y NOMBRES":"RADAS PESANTES DANIEL","ÁREA":"Ssoma","CARGO":"Medico Ocupacional","GUARDIA":"C","Indicador":"INSPECCION","PROGRAMADO":"2","EJECUTADO":"2"},{"@odata.etag":"","ItemInternalId":"30043323-dc5b-4309-8862-c0c4f0893fc6","Mes":"4","Año":"2026","DNI":"40563190","APELLIDOS Y NOMBRES":"ALVAREZ ALVAREZ VICTOR","ÁREA":"Superintendencia","CARGO":"Superintendente de Planta","GUARDIA":"A","Indicador":"DDS","PROGRAMADO":"3","EJECUTADO":"3"},{"@odata.etag":"","ItemInternalId":"2c785139-2c3c-470b-bde0-fbfb730bab3e","Mes":"4","Año":"2026","DNI":"70458908","APELLIDOS Y NOMBRES":"PONCIANO JUSTO JOHNNY","ÁREA":"Producción","CARGO":"Jefe de Planta","GUARDIA":"B","Indicador":"DDS","PROGRAMADO":"3","EJECUTADO":"3"},{"@odata.etag":"","ItemInternalId":"a1fd20aa-4332-40da-aa44-6b9270f888b7","Mes":"4","Año":"2026","DNI":"46578919","APELLIDOS Y NOMBRES":"PALACIOS ALDANA ARELIS","ÁREA":"Ssoma","CARGO":"Jefe de SSOMA","GUARDIA":"B","Indicador":"DDS","PROGRAMADO":"3","EJECUTADO":"3"},{"@odata.etag":"","ItemInternalId":"bb40bdb7-7365-4ffb-b1b3-bc532af7a53d","Mes":"4","Año":"2026","DNI":"48556725","APELLIDOS Y NOMBRES":"GARCIA LAVADO ABEL","ÁREA":"Operaciones","CARGO":"Jefe de Guardia","GUARDIA":"C","Indicador":"DDS","PROGRAMADO":"3","EJECUTADO":"3"},{"@odata.etag":"","ItemInternalId":"9e244f19-646c-4f41-be41-14af8976ff48","Mes":"4","Año":"2026","DNI":"44359932","APELLIDOS Y NOMBRES":"VARGAS CASTRO MIGUEL","ÁREA":"Operaciones","CARGO":"Jefe de Guardia","GUARDIA":"B","Indicador":"DDS","PROGRAMADO":"3","EJECUTADO":"3"},{"@odata.etag":"","ItemInternalId":"5c841bc0-f81c-40dc-af05-0ab00b36a069","Mes":"4","Año":"2026","DNI":"44872088","APELLIDOS Y NOMBRES":"PACHECO HIRAOKA WILMER","ÁREA":"Operaciones","CARGO":"Jefe de Guardia","GUARDIA":"A","Indicador":"DDS","PROGRAMADO":"3","EJECUTADO":"3"},{"@odata.etag":"","ItemInternalId":"a5893560-0d7d-4a06-9269-6f244fcaf872","Mes":"4","Año":"2026","DNI":"19968105","APELLIDOS Y NOMBRES":"SOTO MAPILCA WALTER","ÁREA":"Mantenimiento","CARGO":"Jefe Mantenimiento Mecanico","GUARDIA":"B","Indicador":"DDS","PROGRAMADO":"3","EJECUTADO":"3"},{"@odata.etag":"","ItemInternalId":"f2acb49b-7a2f-4eec-8904-f07b64fbe61b","Mes":"4","Año":"2026","DNI":"18144216","APELLIDOS Y NOMBRES":"CELIO RAMIREZ ANTONIO","ÁREA":"Mantenimiento","CARGO":"Jefe de Mantenimiento Electrico","GUARDIA":"C","Indicador":"DDS","PROGRAMADO":"3","EJECUTADO":"3"},{"@odata.etag":"","ItemInternalId":"e58bcc74-7f03-4f64-98c4-59c2ed6dd1a3","Mes":"4","Año":"2026","DNI":"70086433","APELLIDOS Y NOMBRES":"VEGA CASIANO ROMULO","ÁREA":"Mantenimiento","CARGO":"Jefe de Mantenimiento Vehicular","GUARDIA":"C","Indicador":"DDS","PROGRAMADO":"3","EJECUTADO":"3"},{"@odata.etag":"","ItemInternalId":"94d660f8-b9c7-46db-84dd-6021d3aab5bf","Mes":"4","Año":"2026","DNI":"77675654","APELLIDOS Y NOMBRES":"GORDILLO VELASQUES CRISTPHER","ÁREA":"Metalurgia","CARGO":"Jefe de Metalurgia","GUARDIA":"B","Indicador":"DDS","PROGRAMADO":"3","EJECUTADO":"3"},{"@odata.etag":"","ItemInternalId":"16b63c5b-97d8-42d9-b21b-73612c1fff9b","Mes":"4","Año":"2026","DNI":"46660606","APELLIDOS Y NOMBRES":"GOMEZ ROSAS SAID","ÁREA":"Proyectos","CARGO":"Jefe de Proyectos","GUARDIA":"C","Indicador":"DDS","PROGRAMADO":"3","EJECUTADO":"3"},{"@odata.etag":"","ItemInternalId":"b7117e49-6259-4f8a-8bc7-ff717f7d175c","Mes":"4","Año":"2026","DNI":"74589085","APELLIDOS Y NOMBRES":"FUENTES-DAVILA QUELOPANA MAURICIO","ÁREA":"Administración","CARGO":"Administrador","GUARDIA":"B","Indicador":"DDS","PROGRAMADO":"3","EJECUTADO":"3"},{"@odata.etag":"","ItemInternalId":"65cc6618-55e4-413a-8475-fabec1afd8e8","Mes":"4","Año":"2026","DNI":"46336044","APELLIDOS Y NOMBRES":"ACUÑA QUISPE DAYGURO","ÁREA":"Laboratorio","CARGO":"Jefe de Laboratorio Quimico","GUARDIA":"B","Indicador":"DDS","PROGRAMADO":"3","EJECUTADO":"3"},{"@odata.etag":"","ItemInternalId":"5a2a2aec-fa47-478f-b6b6-84581cda068c","Mes":"4","Año":"2026","DNI":"45789632","APELLIDOS Y NOMBRES":"CARRASCO JARAMILLO NATALIA","ÁREA":"Bienestar Social","CARGO":"Bienestar Social","GUARDIA":"B","Indicador":"DDS","PROGRAMADO":"3","EJECUTADO":"3"},{"@odata.etag":"","ItemInternalId":"7a3096f2-2bae-458c-bff7-75728235ab1f","Mes":"4","Año":"2026","DNI":"73099740","APELLIDOS Y NOMBRES":"UNTIVEROS HUANAY DERLIS","ÁREA":"Almacén","CARGO":"Supervisor Almacen","GUARDIA":"B","Indicador":"DDS","PROGRAMADO":"3","EJECUTADO":"3"},{"@odata.etag":"","ItemInternalId":"ae783c9c-0a6b-43ea-8b93-739dfda61038","Mes":"4","Año":"2026","DNI":"42075790","APELLIDOS Y NOMBRES":"RADAS PESANTES DANIEL","ÁREA":"Ssoma","CARGO":"Medico Ocupacional","GUARDIA":"C","Indicador":"DDS","PROGRAMADO":"3","EJECUTADO":"3"},{"@odata.etag":"","ItemInternalId":"50358df6-158d-4b64-95a6-b6fefdfb21f1","Mes":"4","Año":"2026","DNI":"40563190","APELLIDOS Y NOMBRES":"ALVAREZ ALVAREZ VICTOR","ÁREA":"Superintendencia","CARGO":"Superintendente de Planta","GUARDIA":"A","Indicador":"CAPACITACION SSO","PROGRAMADO":"1","EJECUTADO":"1"},{"@odata.etag":"","ItemInternalId":"4fb86b3b-4520-41c4-ae08-27008e5bbe42","Mes":"4","Año":"2026","DNI":"70458908","APELLIDOS Y NOMBRES":"PONCIANO JUSTO JOHNNY","ÁREA":"Producción","CARGO":"Jefe de Planta","GUARDIA":"B","Indicador":"CAPACITACION SSO","PROGRAMADO":"1","EJECUTADO":"1"},{"@odata.etag":"","ItemInternalId":"2f7cadb3-877c-42af-b339-d7c934cc29ba","Mes":"4","Año":"2026","DNI":"46578919","APELLIDOS Y NOMBRES":"PALACIOS ALDANA ARELIS","ÁREA":"Ssoma","CARGO":"Jefe de SSOMA","GUARDIA":"B","Indicador":"CAPACITACION SSO","PROGRAMADO":"1","EJECUTADO":"1"},{"@odata.etag":"","ItemInternalId":"8b9bc696-a690-45ed-a75e-ac45eb7ae8eb","Mes":"4","Año":"2026","DNI":"48556725","APELLIDOS Y NOMBRES":"GARCIA LAVADO ABEL","ÁREA":"Operaciones","CARGO":"Jefe de Guardia","GUARDIA":"C","Indicador":"CAPACITACION SSO","PROGRAMADO":"1","EJECUTADO":"1"},{"@odata.etag":"","ItemInternalId":"25acc351-512b-49a8-8cb8-efb5bd09942f","Mes":"4","Año":"2026","DNI":"44359932","APELLIDOS Y NOMBRES":"VARGAS CASTRO MIGUEL","ÁREA":"Operaciones","CARGO":"Jefe de Guardia","GUARDIA":"B","Indicador":"CAPACITACION SSO","PROGRAMADO":"1","EJECUTADO":"1"},{"@odata.etag":"","ItemInternalId":"9bd6eff3-ec4c-4832-9361-72f9563074c6","Mes":"4","Año":"2026","DNI":"44872088","APELLIDOS Y NOMBRES":"PACHECO HIRAOKA WILMER","ÁREA":"Operaciones","CARGO":"Jefe de Guardia","GUARDIA":"A","Indicador":"CAPACITACION SSO","PROGRAMADO":"1","EJECUTADO":"1"},{"@odata.etag":"","ItemInternalId":"a5355e45-a59d-42d3-b3cd-d251adb12504","Mes":"4","Año":"2026","DNI":"19968105","APELLIDOS Y NOMBRES":"SOTO MAPILCA WALTER","ÁREA":"Mantenimiento","CARGO":"Jefe Mantenimiento Mecanico","GUARDIA":"B","Indicador":"CAPACITACION SSO","PROGRAMADO":"1","EJECUTADO":"1"},{"@odata.etag":"","ItemInternalId":"fa5d0846-e2ab-4b70-a0c0-87d67b9050a6","Mes":"4","Año":"2026","DNI":"18144216","APELLIDOS Y NOMBRES":"CELIO RAMIREZ ANTONIO","ÁREA":"Mantenimiento","CARGO":"Jefe de Mantenimiento Electrico","GUARDIA":"C","Indicador":"CAPACITACION SSO","PROGRAMADO":"1","EJECUTADO":"1"},{"@odata.etag":"","ItemInternalId":"c2acce08-101b-414e-afee-790db0a6e889","Mes":"4","Año":"2026","DNI":"70086433","APELLIDOS Y NOMBRES":"VEGA CASIANO ROMULO","ÁREA":"Mantenimiento","CARGO":"Jefe de Mantenimiento Vehicular","GUARDIA":"C","Indicador":"CAPACITACION SSO","PROGRAMADO":"1","EJECUTADO":"1"},{"@odata.etag":"","ItemInternalId":"a40ea717-d4db-4ec7-8d84-a27b3476fc62","Mes":"4","Año":"2026","DNI":"77675654","APELLIDOS Y NOMBRES":"GORDILLO VELASQUES CRISTPHER","ÁREA":"Metalurgia","CARGO":"Jefe de Metalurgia","GUARDIA":"B","Indicador":"CAPACITACION SSO","PROGRAMADO":"1","EJECUTADO":"1"},{"@odata.etag":"","ItemInternalId":"cc017b1c-2150-4e22-a557-9e6750bed419","Mes":"4","Año":"2026","DNI":"46660606","APELLIDOS Y NOMBRES":"GOMEZ ROSAS SAID","ÁREA":"Proyectos","CARGO":"Jefe de Proyectos","GUARDIA":"C","Indicador":"CAPACITACION SSO","PROGRAMADO":"1","EJECUTADO":"1"},{"@odata.etag":"","ItemInternalId":"9092ab37-4b68-45dd-823e-c4d5b7219421","Mes":"4","Año":"2026","DNI":"74589085","APELLIDOS Y NOMBRES":"FUENTES-DAVILA QUELOPANA MAURICIO","ÁREA":"Administración","CARGO":"Administrador","GUARDIA":"B","Indicador":"CAPACITACION SSO","PROGRAMADO":"1","EJECUTADO":"1"},{"@odata.etag":"","ItemInternalId":"c861d686-4aa3-44dc-9ba4-6cf70e4b5273","Mes":"4","Año":"2026","DNI":"46336044","APELLIDOS Y NOMBRES":"ACUÑA QUISPE DAYGURO","ÁREA":"Laboratorio","CARGO":"Jefe de Laboratorio Quimico","GUARDIA":"B","Indicador":"CAPACITACION SSO","PROGRAMADO":"1","EJECUTADO":"1"},{"@odata.etag":"","ItemInternalId":"a5cb4228-6be4-4e28-9edc-2b98bec09321","Mes":"4","Año":"2026","DNI":"45789632","APELLIDOS Y NOMBRES":"CARRASCO JARAMILLO NATALIA","ÁREA":"Bienestar Social","CARGO":"Bienestar Social","GUARDIA":"B","Indicador":"CAPACITACION SSO","PROGRAMADO":"1","EJECUTADO":"1"},{"@odata.etag":"","ItemInternalId":"877f2d44-7b1f-4a9e-a4bd-225d4b732cb4","Mes":"4","Año":"2026","DNI":"73099740","APELLIDOS Y NOMBRES":"UNTIVEROS HUANAY DERLIS","ÁREA":"Almacén","CARGO":"Supervisor Almacen","GUARDIA":"B","Indicador":"CAPACITACION SSO","PROGRAMADO":"1","EJECUTADO":"1"},{"@odata.etag":"","ItemInternalId":"f1568eef-736c-4eef-a237-ef9564911581","Mes":"4","Año":"2026","DNI":"42075790","APELLIDOS Y NOMBRES":"RADAS PESANTES DANIEL","ÁREA":"Ssoma","CARGO":"Medico Ocupacional","GUARDIA":"C","Indicador":"CAPACITACION SSO","PROGRAMADO":"1","EJECUTADO":"1"},{"@odata.etag":"","ItemInternalId":"607cba0d-df33-4771-8f01-c76bb91fd597","Mes":"4","Año":"2026","DNI":"40563190","APELLIDOS Y NOMBRES":"ALVAREZ ALVAREZ VICTOR","ÁREA":"Superintendencia","CARGO":"Superintendente de Planta","GUARDIA":"A","Indicador":"RACs","PROGRAMADO":"3","EJECUTADO":"3"},{"@odata.etag":"","ItemInternalId":"2fa0f7d7-8abd-49bb-80de-5e1446c1d40a","Mes":"4","Año":"2026","DNI":"70458908","APELLIDOS Y NOMBRES":"PONCIANO JUSTO JOHNNY","ÁREA":"Producción","CARGO":"Jefe de Planta","GUARDIA":"B","Indicador":"RACs","PROGRAMADO":"3","EJECUTADO":"3"},{"@odata.etag":"","ItemInternalId":"8dedfb9b-db40-457f-a3d9-f13157d47068","Mes":"4","Año":"2026","DNI":"46578919","APELLIDOS Y NOMBRES":"PALACIOS ALDANA ARELIS","ÁREA":"Ssoma","CARGO":"Jefe de SSOMA","GUARDIA":"B","Indicador":"RACs","PROGRAMADO":"3","EJECUTADO":"3"},{"@odata.etag":"","ItemInternalId":"7719c7f8-9d34-427e-a394-6c770a31b11c","Mes":"4","Año":"2026","DNI":"48556725","APELLIDOS Y NOMBRES":"GARCIA LAVADO ABEL","ÁREA":"Operaciones","CARGO":"Jefe de Guardia","GUARDIA":"C","Indicador":"RACs","PROGRAMADO":"3","EJECUTADO":"3"},{"@odata.etag":"","ItemInternalId":"eb960a34-4be7-4fd9-b144-6b073fcca047","Mes":"4","Año":"2026","DNI":"44359932","APELLIDOS Y NOMBRES":"VARGAS CASTRO MIGUEL","ÁREA":"Operaciones","CARGO":"Jefe de Guardia","GUARDIA":"B","Indicador":"RACs","PROGRAMADO":"3","EJECUTADO":"3"},{"@odata.etag":"","ItemInternalId":"c5a51cd8-603c-40fd-8011-51911f979971","Mes":"4","Año":"2026","DNI":"44872088","APELLIDOS Y NOMBRES":"PACHECO HIRAOKA WILMER","ÁREA":"Operaciones","CARGO":"Jefe de Guardia","GUARDIA":"A","Indicador":"RACs","PROGRAMADO":"3","EJECUTADO":"3"},{"@odata.etag":"","ItemInternalId":"c98b49b6-334c-45dd-abb2-fa0b8672475c","Mes":"4","Año":"2026","DNI":"19968105","APELLIDOS Y NOMBRES":"SOTO MAPILCA WALTER","ÁREA":"Mantenimiento","CARGO":"Jefe Mantenimiento Mecanico","GUARDIA":"B","Indicador":"RACs","PROGRAMADO":"3","EJECUTADO":"3"},{"@odata.etag":"","ItemInternalId":"dcfdbb95-af38-46f7-9faa-c1e9890f187a","Mes":"4","Año":"2026","DNI":"18144216","APELLIDOS Y NOMBRES":"CELIO RAMIREZ ANTONIO","ÁREA":"Mantenimiento","CARGO":"Jefe de Mantenimiento Electrico","GUARDIA":"C","Indicador":"RACs","PROGRAMADO":"3","EJECUTADO":"3"},{"@odata.etag":"","ItemInternalId":"cab08cd8-4649-4fa8-94b4-a73c69d5c147","Mes":"4","Año":"2026","DNI":"70086433","APELLIDOS Y NOMBRES":"VEGA CASIANO ROMULO","ÁREA":"Mantenimiento","CARGO":"Jefe de Mantenimiento Vehicular","GUARDIA":"C","Indicador":"RACs","PROGRAMADO":"3","EJECUTADO":"3"},{"@odata.etag":"","ItemInternalId":"616f3c4e-b572-466a-b41e-84b0801cb72a","Mes":"4","Año":"2026","DNI":"77675654","APELLIDOS Y NOMBRES":"GORDILLO VELASQUES CRISTPHER","ÁREA":"Metalurgia","CARGO":"Jefe de Metalurgia","GUARDIA":"B","Indicador":"RACs","PROGRAMADO":"3","EJECUTADO":"3"},{"@odata.etag":"","ItemInternalId":"f7072f70-4e84-4737-a5a8-ec2ca3e52437","Mes":"4","Año":"2026","DNI":"46660606","APELLIDOS Y NOMBRES":"GOMEZ ROSAS SAID","ÁREA":"Proyectos","CARGO":"Jefe de Proyectos","GUARDIA":"C","Indicador":"RACs","PROGRAMADO":"3","EJECUTADO":"3"},{"@odata.etag":"","ItemInternalId":"0ff5eec8-1aa1-4d74-b16f-e11e2985b398","Mes":"4","Año":"2026","DNI":"74589085","APELLIDOS Y NOMBRES":"FUENTES-DAVILA QUELOPANA MAURICIO","ÁREA":"Administración","CARGO":"Administrador","GUARDIA":"B","Indicador":"RACs","PROGRAMADO":"3","EJECUTADO":"3"},{"@odata.etag":"","ItemInternalId":"2edf8830-89f4-4408-a4f6-e4078206abd2","Mes":"4","Año":"2026","DNI":"46336044","APELLIDOS Y NOMBRES":"ACUÑA QUISPE DAYGURO","ÁREA":"Laboratorio","CARGO":"Jefe de Laboratorio Quimico","GUARDIA":"B","Indicador":"RACs","PROGRAMADO":"3","EJECUTADO":"3"},{"@odata.etag":"","ItemInternalId":"791b6a32-6e4d-4275-a48c-9e4b7a96aaf0","Mes":"4","Año":"2026","DNI":"45789632","APELLIDOS Y NOMBRES":"CARRASCO JARAMILLO NATALIA","ÁREA":"Bienestar Social","CARGO":"Bienestar Social","GUARDIA":"B","Indicador":"RACs","PROGRAMADO":"3","EJECUTADO":"3"},{"@odata.etag":"","ItemInternalId":"dffecd11-5a2e-4234-9330-b7fe902b301d","Mes":"4","Año":"2026","DNI":"73099740","APELLIDOS Y NOMBRES":"UNTIVEROS HUANAY DERLIS","ÁREA":"Almacén","CARGO":"Supervisor Almacen","GUARDIA":"B","Indicador":"RACs","PROGRAMADO":"3","EJECUTADO":"3"},{"@odata.etag":"","ItemInternalId":"d9efeeb2-9e45-4441-bf2b-5252e90c1a04","Mes":"4","Año":"2026","DNI":"42075790","APELLIDOS Y NOMBRES":"RADAS PESANTES DANIEL","ÁREA":"Ssoma","CARGO":"Medico Ocupacional","GUARDIA":"C","Indicador":"RACs","PROGRAMADO":"3","EJECUTADO":"3"}]}